{"version": "1", "message": "ERROR: Hidden Testcases server unreachable.", "problem_id": "ads2_m7_a1_1", "user_id": "someshwarthuma", "score": {"sample": {"0": {"execution_time": 1.7112147808074951, "passed": false}, "1": {"execution_time": 0.29120612144470215, "passed": false}, "2": {"execution_time": 0.4223010540008545, "passed": false}, "3": {"execution_time": 0.2892129421234131, "passed": false}, "4": {"execution_time": 0.2952156066894531, "passed": false}, "5": {"execution_time": 0.29120659828186035, "passed": false}}}, "check_style_score": "0/1"}